tttui/__init__.py
tttui/__main__.py
tttui/config.py
tttui/game.py
tttui/menu.py
tttui/storage.py
tttui/ui.py
tttui/languages/english.txt
tttui/languages/italian.txt
tttui/languages/japanese.txt
tttui/languages/spanish.txt
tttui/quotes/english.txt
tttui/quotes/italian.txt
tttui/quotes/japanese.txt
tttui/quotes/spanish.txt
tttui-1.0.3.dist-info/licenses/LICENSE
tttui-1.0.3.dist-info/METADATA
tttui-1.0.3.dist-info/WHEEL
tttui-1.0.3.dist-info/entry_points.txt
tttui-1.0.3.dist-info/top_level.txt
tttui-1.0.3.dist-info/RECORD
