Metadata-Version: 2.4
Name: tttui
Version: 1.0.3
Summary: A Terminal-based Typing Test (TUI)
Home-page: https://github.com/ReidoBoss/tttui
Author: ReidoBoss
Author-email: bryansagarino222@gmail.com
Classifier: Programming Language :: Python :: 3
Classifier: License :: OSI Approved :: MIT License
Classifier: Operating System :: OS Independent
Classifier: Environment :: Console
Classifier: Environment :: Console :: Curses
Classifier: Topic :: Terminals
Requires-Python: >=3.7
License-File: LICENSE
Dynamic: license-file
